pycommandparse/__init__.py
pycommandparse/command.py
pycommandparse/errors.py
pycommandparse/parsers/__init__.py
pycommandparse/parsers/baseparser.py
pycommandparse-0.2.0.dist-info/WHEEL
pycommandparse-0.2.0.dist-info/METADATA
pycommandparse-0.2.0.dist-info/RECORD
