Metadata-Version: 2.1
Name: pycommandparse
Version: 0.2.0
Summary: A collection of classes that help parse commands.
License: MIT
Author: thelegendbeacon
Requires-Python: >=3.6,<4.0
Classifier: License :: OSI Approved :: MIT License
Classifier: Programming Language :: Python :: 3
Classifier: Programming Language :: Python :: 3.6
Classifier: Programming Language :: Python :: 3.7
Classifier: Programming Language :: Python :: 3.8
Classifier: Programming Language :: Python :: 3.9
